src/ADC_DAC/DAC_AD5061/DAC_AD5061.v
////////////////////////////////////////////////////////////////////////////////////////////
module DAC_AD5061 (
	input CLK,
	input LATCH,
	input [15:0] VALUE,
	output reg SYNC_DAC,
	output reg CLK_DAC,
	output reg SDO_DAC
	);
	//
	reg [15:0] ctr_clk_delay;
	reg [11:0] index;
	reg [23:0] value_temp;
	reg [4:0] state;
	//
	reg hri1; reg hri2; reg hri3; reg hri4;
	wire latch_start;
	wire clk_dac_re;
	wire clk_dac_fe;	
	//
	assign	latch_start = (hri1 && !hri2);
	assign	clk_dac_re = (hri3 && !hri4);
	assign	clk_dac_fe = (!hri3 && hri4);
	//	
	initial
	begin
		
		SYNC_DAC <= 1;
		CLK_DAC <= 0;
		SDO_DAC <= 0;
		index <= 23;
		value_temp <= 24'b00000000_00000000_00000000;// Datasheet S.15
		state <= 0;
		ctr_clk_delay <= 1;
		//
		hri1 <= 0; hri2 <= 0; hri3 <= 0; hri4 <= 0; 
	end	
	//
	always	@(posedge CLK)
	begin
	// Impulsauswertung
	hri1 <= LATCH;
	hri2 <= hri1;
	hri3 <= CLK_DAC;
	hri4 <= hri3;
	//
	if (state == 0) 
		begin
		SYNC_DAC <= 1;
		index <= 23;
		value_temp <= 24'b00000000_00000000_00000000;// Datasheet S.15
		ctr_clk_delay <= 1;
		//
		if(latch_start) 
			begin
			value_temp[15:0] <= VALUE[15:0];
			SYNC_DAC <= 0;
			state <= 1;
			end
		//
		end
	//
	if (state == 1) 
		begin
		ctr_clk_delay <= ctr_clk_delay + 1;
		if (ctr_clk_delay == 3) 
			begin
			ctr_clk_delay <= 1;
			CLK_DAC <= !CLK_DAC;
			end
		//
		SDO_DAC <= value_temp[index];
		if (clk_dac_fe && (index > 0)) index <= index - 1;
		//
		if (clk_dac_fe && (index == 0)) 
			begin
			ctr_clk_delay <= 1;
			state <= 2;
			end
		end
	//
	if (state == 2) 
		begin
		ctr_clk_delay <= ctr_clk_delay + 1;
		if (ctr_clk_delay == 3) 
			begin
			ctr_clk_delay <= 1;
			SYNC_DAC <= 1;
			SDO_DAC <= 0;
			state <= 0;
			end
		end
	//
	end
endmodule
////////////////////////////////////////////////////////////////////////////////////////////

src/ADC_DAC/DAC_AD5061/ICARUS_TB.v
`include "DAC_AD5061.v"
// http://verilogtutorial.blogspot.ch/2012/09/verilog-timescale-system-tasks.html
`timescale 10ns/1ns
//
module ICARUS_TB;
	//
	integer file;
	reg clk;
	reg latch;
	reg [15:0] value;
	wire sync_dac;
	wire clk_dac;
	wire sdo_dac;
	//
	initial 
	begin
		clk <= 1;
		latch <= 0;
		value <= 16'h4321;
		//
		$dumpfile("vcd\\\icarus_tb.vcd"); 
		$dumpvars(0, ICARUS_TB); 
		//
		#20 latch <= 1;
		#20 latch <= 0;
		//
		#500 $finish; 
	end 
	//
	always #1 clk <= !clk;
	//
	DAC_AD5061 dac_ad5061(
					clk,
	                latch,
					value,
			        sync_dac,
			        clk_dac,
			        sdo_dac
					);		
	//
endmodule
//
/*
cd D:\Dropbox\ABBTS_DA\FPGA\FPGA_DA_MODUL_MAX1000_00_02\src\ADC_DAC\DAC_AD5061
C:\iverilog\bin\iverilog -s ICARUS_TB -o icarus_tb.o ICARUS_TB.v
C:\iverilog\bin\vvp icarus_tb.o
*/

src/ADC_DAC/DAC_AD5061/vcd/icarus_tb.vcd
$date
	Tue May 15 11:20:11 2018
$end
$version
	Icarus Verilog
$end
$timescale
	1ns
$end
$scope module ICARUS_TB $end
$var wire 1 ! sync_dac $end
$var wire 1 " sdo_dac $end
$var wire 1 # clk_dac $end
$var reg 1 $ clk $end
$var reg 1 % latch $end
$var reg 16 & value [15:0] $end
$scope module dac_ad5061 $end
$var wire 1 $ CLK $end
$var wire 1 % LATCH $end
$var wire 16 ' VALUE [15:0] $end
$var wire 1 ( clk_dac_fe $end
$var wire 1 ) clk_dac_re $end
$var wire 1 * latch_start $end
$var reg 1 # CLK_DAC $end
$var reg 1 " SDO_DAC $end
$var reg 1 ! SYNC_DAC $end
$var reg 16 + ctr_clk_delay [15:0] $end
$var reg 1 , hri1 $end
$var reg 1 - hri2 $end
$var reg 1 . hri3 $end
$var reg 1 / hri4 $end
$var reg 12 0 index [11:0] $end
$var reg 5 1 state [4:0] $end
$var reg 24 2 value_temp [23:0] $end
$upscope $end
$upscope $end
$enddefinitions $end
#0
$dumpvars
b0 2
b0 1
b10111 0
0/
0.
0-
0,
b1 +
0*
0)
0(
b100001100100001 '
b100001100100001 &
0%
1$
0#
0"
1!
$end
#10
0$
#20
1$
#30
0$
#40
1$
#50
0$
#60
1$
#70
0$
#80
1$
#90
0$
#100
1$
#110
0$
#120
1$
#130
0$
#140
1$
#150
0$
#160
1$
#170
0$
#180
1$
#190
0$
#200
1*
1,
1$
1%
#210
0$
#220
0*
b1 1
0!
b11000000000000 2
1-
1$
#230
0$
#240
b10 +
1$
#250
0$
#260
b11 +
1$
#270
0$
#280
1#
b1 +
1$
#290
0$
#300
1)
b10 +
1.
1$
#310
0$
#320
0)
b11 +
1/
1$
#330
0$
#340
0#
b1 +
1$
#350
0$
#360
1(
b10 +
0.
1$
#370
0$
#380
0(
b10110 0
b11 +
0/
1$
#390
0$
#400
1#
b1 +
0,
1$
0%
#410
0$
#420
1)
b10 +
1.
0-
1$
#430
0$
#440
0)
b11 +
1/
1$
#450
0$
#460
0#
b1 +
1$
#470
0$
#480
1(
b10 +
0.
1$
#490
0$
#500
0(
b10101 0
b11 +
0/
1$
#510
0$
#520
1#
b1 +
1$
#530
0$
#540
1)
b10 +
1.
1$
#550
0$
#560
0)
b11 +
1/
1$
#570
0$
#580
0#
b1 +
1$
#590
0$
#600
1(
b10 +
0.
1$
#610
0$
#620
0(
b10100 0
b11 +
0/
1$
#630
0$
#640
1#
b1 +
1$
#650
0$
#660
1)
b10 +
1.
1$
#670
0$
#680
0)
b11 +
1/
1$
#690
0$
#700
0#
b1 +
1$
#710
0$
#720
1(
b10 +
0.
1$
#730
0$
#740
0(
b10011 0
b11 +
0/
1$
#750
0$
#760
1#
b1 +
1$
#770
0$
#780
1)
b10 +
1.
1$
#790
0$
#800
0)
b11 +
1/
1$
#810
0$
#820
0#
b1 +
1$
#830
0$
#840
1(
b10 +
0.
1$
#850
0$
#860
0(
b10010 0
b11 +
0/
1$
#870
0$
#880
1#
b1 +
1$
#890
0$
#900
1)
b10 +
1.
1$
#910
0$
#920
0)
b11 +
1/
1$
#930
0$
#940
0#
b1 +
1$
#950
0$
#960
1(
b10 +
0.
1$
#970
0$
#980
0(
b10001 0
b11 +
0/
1$
#990
0$
#1000
1#
b1 +
1$
#1010
0$
#1020
1)
b10 +
1.
1$
#1030
0$
#1040
0)
b11 +
1/
1$
#1050
0$
#1060
0#
b1 +
1$
#1070
0$
#1080
1(
b10 +
0.
1$
#1090
0$
#1100
0(
b10000 0
b11 +
0/
1$
#1110
0$
#1120
1#
b1 +
1$
#1130
0$
#1140
1)
b10 +
1.
1$
#1150
0$
#1160
0)
b11 +
1/
1$
#1170
0$
#1180
0#
b1 +
1$
#1190
0$
#1200
1(
b10 +
0.
1$
#1210
0$
#1220
0(
b1111 0
b11 +
0/
1$
#1230
0$
#1240
1#
b1 +
1$
#1250
0$
#1260
1)
b10 +
1.
1$
#1270
0$
#1280
0)
b11 +
1/
1$
#1290
0$
#1300
0#
b1 +
1$
#1310
0$
#1320
1(
b10 +
0.
1$
#1330
0$
#1340
0(
b1110 0
b11 +
0/
1$
#1350
0$
#1360
1#
b1 +
1$
#1370
0$
#1380
1)
b10 +
1.
1$
#1390
0$
#1400
0)
b11 +
1/
1$
#1410
0$
#1420
0#
b1 +
1$
#1430
0$
#1440
1(
b10 +
0.
1$
#1450
0$
#1460
0(
b1101 0
b11 +
0/
1$
#1470
0$
#1480
1"
1#
b1 +
1$
#1490
0$
#1500
1)
b10 +
1.
1$
#1510
0$
#1520
0)
b11 +
1/
1$
#1530
0$
#1540
0#
b1 +
1$
#1550
0$
#1560
1(
b10 +
0.
1$
#1570
0$
#1580
0(
b1100 0
b11 +
0/
1$
#1590
0$
#1600
1#
b1 +
1$
#1610
0$
#1620
1)
b10 +
1.
1$
#1630
0$
#1640
0)
b11 +
1/
1$
#1650
0$
#1660
0#
b1 +
1$
#1670
0$
#1680
1(
b10 +
0.
1$
#1690
0$
#1700
0(
b1011 0
b11 +
0/
1$
#1710
0$
#1720
0"
1#
b1 +
1$
#1730
0$
#1740
1)
b10 +
1.
1$
#1750
0$
#1760
0)
b11 +
1/
1$
#1770
0$
#1780
0#
b1 +
1$
#1790
0$
#1800
1(
b10 +
0.
1$
#1810
0$
#1820
0(
b1010 0
b11 +
0/
1$
#1830
0$
#1840
1#
b1 +
1$
#1850
0$
#1860
1)
b10 +
1.
1$
#1870
0$
#1880
0)
b11 +
1/
1$
#1890
0$
#1900
0#
b1 +
1$
#1910
0$
#1920
1(
b10 +
0.
1$
#1930
0$
#1940
0(
b1001 0
b11 +
0/
1$
#1950
0$
#1960
1#
b1 +
1$
#1970
0$
#1980
1)
b10 +
1.
1$
#1990
0$
#2000
0)
b11 +
1/
1$
#2010
0$
#2020
0#
b1 +
1$
#2030
0$
#2040
1(
b10 +
0.
1$
#2050
0$
#2060
0(
b1000 0
b11 +
0/
1$
#2070
0$
#2080
1#
b1 +
1$
#2090
0$
#2100
1)
b10 +
1.
1$
#2110
0$
#2120
0)
b11 +
1/
1$
#2130
0$
#2140
0#
b1 +
1$
#2150
0$
#2160
1(
b10 +
0.
1$
#2170
0$
#2180
0(
b111 0
b11 +
0/
1$
#2190
0$
#2200
1#
b1 +
1$
#2210
0$
#2220
1)
b10 +
1.
1$
#2230
0$
#2240
0)
b11 +
1/
1$
#2250
0$
#2260
0#
b1 +
1$
#2270
0$
#2280
1(
b10 +
0.
1$
#2290
0$
#2300
0(
b110 0
b11 +
0/
1$
#2310
0$
#2320
1#
b1 +
1$
#2330
0$
#2340
1)
b10 +
1.
1$
#2350
0$
#2360
0)
b11 +
1/
1$
#2370
0$
#2380
0#
b1 +
1$
#2390
0$
#2400
1(
b10 +
0.
1$
#2410
0$
#2420
0(
b101 0
b11 +
0/
1$
#2430
0$
#2440
1#
b1 +
1$
#2450
0$
#2460
1)
b10 +
1.
1$
#2470
0$
#2480
0)
b11 +
1/
1$
#2490
0$
#2500
0#
b1 +
1$
#2510
0$
#2520
1(
b10 +
0.
1$
#2530
0$
#2540
0(
b100 0
b11 +
0/
1$
#2550
0$
#2560
1#
b1 +
1$
#2570
0$
#2580
1)
b10 +
1.
1$
#2590
0$
#2600
0)
b11 +
1/
1$
#2610
0$
#2620
0#
b1 +
1$
#2630
0$
#2640
1(
b10 +
0.
1$
#2650
0$
#2660
0(
b11 0
b11 +
0/
1$
#2670
0$
#2680
1#
b1 +
1$
#2690
0$
#2700
1)
b10 +
1.
1$
#2710
0$
#2720
0)
b11 +
1/
1$
#2730
0$
#2740
0#
b1 +
1$
#2750
0$
#2760
1(
b10 +
0.
1$
#2770
0$
#2780
0(
b10 0
b11 +
0/
1$
#2790
0$
#2800
1#
b1 +
1$
#2810
0$
#2820
1)
b10 +
1.
1$
#2830
0$
#2840
0)
b11 +
1/
1$
#2850
0$
#2860
0#
b1 +
1$
#2870
0$
#2880
1(
b10 +
0.
1$
#2890
0$
#2900
0(
b1 0
b11 +
0/
1$
#2910
0$
#2920
1#
b1 +
1$
#2930
0$
#2940
1)
b10 +
1.
1$
#2950
0$
#2960
0)
b11 +
1/
1$
#2970
0$
#2980
0#
b1 +
1$
#2990
0$
#3000
1(
b10 +
0.
1$
#3010
0$
#3020
0(
b0 0
b11 +
0/
1$
#3030
0$
#3040
1#
b1 +
1$
#3050
0$
#3060
1)
b10 +
1.
1$
#3070
0$
#3080
0)
b11 +
1/
1$
#3090
0$
#3100
0#
b1 +
1$
#3110
0$
#3120
1(
b10 +
0.
1$
#3130
0$
#3140
0(
b10 1
b1 +
0/
1$
#3150
0$
#3160
b10 +
1$
#3170
0$
#3180
b11 +
1$
#3190
0$
#3200
b0 1
1!
b1 +
1$
#3210
0$
#3220
b0 2
b10111 0
1$
